sbenchmark_dependency_test_one/__init__.py
sbenchmark_dependency_test_one-1.0.3.dist-info/METADATA
sbenchmark_dependency_test_one-1.0.3.dist-info/WHEEL
sbenchmark_dependency_test_one-1.0.3.dist-info/top_level.txt
sbenchmark_dependency_test_one-1.0.3.dist-info/RECORD
