Metadata-Version: 2.4
Name: sbenchmark-dependency-test-one
Version: 1.0.3
Summary: Python test library to be used with sbenchmark suite have testable dependency version number.
Author: Felix Reichmann
Keywords: dependency,sbenchmark
Classifier: Programming Language :: Python :: 3
Classifier: Programming Language :: Python :: 3 :: Only
Classifier: License :: OSI Approved :: MIT License
Classifier: Operating System :: OS Independent
Requires-Python: >=3.12
